odoo/addons/ssi_kpi/README.rst
odoo/addons/ssi_kpi/__init__.py
odoo/addons/ssi_kpi/__manifest__.py
odoo/addons/ssi_kpi/menu.xml
odoo/addons/ssi_kpi/data/approval_department_template_data.xml
odoo/addons/ssi_kpi/data/approval_employee_template_data.xml
odoo/addons/ssi_kpi/data/ir_sequence_data.xml
odoo/addons/ssi_kpi/data/policy_kpi_department_appraisal_template_data.xml
odoo/addons/ssi_kpi/data/policy_kpi_department_template_data.xml
odoo/addons/ssi_kpi/data/policy_kpi_employee_appraisal_template_data.xml
odoo/addons/ssi_kpi/data/policy_kpi_employee_template_data.xml
odoo/addons/ssi_kpi/data/sequence_kpi_department_template_data.xml
odoo/addons/ssi_kpi/data/sequence_kpi_employee_template_data.xml
odoo/addons/ssi_kpi/models/__init__.py
odoo/addons/ssi_kpi/models/kpi_appraisal_line_mixin.py
odoo/addons/ssi_kpi/models/kpi_appraisal_mixin.py
odoo/addons/ssi_kpi/models/kpi_department.py
odoo/addons/ssi_kpi/models/kpi_employee.py
odoo/addons/ssi_kpi/models/kpi_item.py
odoo/addons/ssi_kpi/models/kpi_line_mixin.py
odoo/addons/ssi_kpi/models/kpi_line_score_range_mixin.py
odoo/addons/ssi_kpi/models/kpi_mixin.py
odoo/addons/ssi_kpi/models/kpi_score_categ.py
odoo/addons/ssi_kpi/models/kpi_score_categ_range.py
odoo/addons/ssi_kpi/models/kpi_score_categ_range_value.py
odoo/addons/ssi_kpi/models/kpi_template.py
odoo/addons/ssi_kpi/models/kpi_template_line.py
odoo/addons/ssi_kpi/models/kpi_template_score_range.py
odoo/addons/ssi_kpi/security/ir.model.access.csv
odoo/addons/ssi_kpi/security/ir_module_category_data.xml
odoo/addons/ssi_kpi/security/ir_rule_data.xml
odoo/addons/ssi_kpi/security/res_group_data.xml
odoo/addons/ssi_kpi/static/description/icon.png
odoo/addons/ssi_kpi/views/kpi_department_appraisal_line_views.xml
odoo/addons/ssi_kpi/views/kpi_department_appraisal_views.xml
odoo/addons/ssi_kpi/views/kpi_department_line_views.xml
odoo/addons/ssi_kpi/views/kpi_department_views.xml
odoo/addons/ssi_kpi/views/kpi_employee_appraisal_line_views.xml
odoo14_addon_ssi_kpi-14.0.1.2.0.dist-info/METADATA
odoo14_addon_ssi_kpi-14.0.1.2.0.dist-info/WHEEL
odoo14_addon_ssi_kpi-14.0.1.2.0.dist-info/top_level.txt
odoo14_addon_ssi_kpi-14.0.1.2.0.dist-info/RECORD
